odoo/addons/account_statement_import_file_reconciliation_widget/README.rst
odoo/addons/account_statement_import_file_reconciliation_widget/__init__.py
odoo/addons/account_statement_import_file_reconciliation_widget/__manifest__.py
odoo/addons/account_statement_import_file_reconciliation_widget/i18n/account_statement_import_file_reconciliation_widget.pot
odoo/addons/account_statement_import_file_reconciliation_widget/i18n/da.po
odoo/addons/account_statement_import_file_reconciliation_widget/i18n/fr.po
odoo/addons/account_statement_import_file_reconciliation_widget/readme/CONTRIBUTORS.rst
odoo/addons/account_statement_import_file_reconciliation_widget/readme/DESCRIPTION.rst
odoo/addons/account_statement_import_file_reconciliation_widget/readme/INSTALL.rst
odoo/addons/account_statement_import_file_reconciliation_widget/static/description/bank_statement_import_start_reconcile.png
odoo/addons/account_statement_import_file_reconciliation_widget/static/description/icon.png
odoo/addons/account_statement_import_file_reconciliation_widget/static/description/index.html
odoo/addons/account_statement_import_file_reconciliation_widget/wizards/__init__.py
odoo/addons/account_statement_import_file_reconciliation_widget/wizards/account_statement_import.py
odoo/addons/account_statement_import_file_reconciliation_widget/wizards/account_statement_import_view.xml
odoo_addon_account_statement_import_file_reconciliation_widget-15.0.1.0.0.6.dist-info/METADATA
odoo_addon_account_statement_import_file_reconciliation_widget-15.0.1.0.0.6.dist-info/WHEEL
odoo_addon_account_statement_import_file_reconciliation_widget-15.0.1.0.0.6.dist-info/top_level.txt
odoo_addon_account_statement_import_file_reconciliation_widget-15.0.1.0.0.6.dist-info/RECORD
