Metadata-Version: 2.1
Name: odoo-addon-account-statement-import-file-reconciliation-widget
Version: 15.0.1.0.0.6
Summary: Import Statement Files and Go Direct to Reconciliation
Home-page: https://github.com/OCA/bank-statement-import
Author: Akretion, Odoo Community Association (OCA)
Author-email: support@odoo-community.org
License: AGPL-3
Platform: UNKNOWN
Classifier: Programming Language :: Python
Classifier: Framework :: Odoo
Classifier: Framework :: Odoo :: 15.0
Classifier: License :: OSI Approved :: GNU Affero General Public License v3
Requires-Python: >=3.8
Requires-Dist: odoo-addon-account-reconciliation-widget <15.1dev,>=15.0dev
Requires-Dist: odoo-addon-account-statement-import <15.1dev,>=15.0dev
Requires-Dist: odoo <15.1dev,>=15.0a
